MANIFEST.in
setup.cfg
setup.py
sculpt/__init__.py
sculpt.ajax.egg-info/PKG-INFO
sculpt.ajax.egg-info/SOURCES.txt
sculpt.ajax.egg-info/dependency_links.txt
sculpt.ajax.egg-info/requires.txt
sculpt.ajax.egg-info/top_level.txt
sculpt/ajax/__init__.py
sculpt/ajax/ajax_test.py
sculpt/ajax/enumerations.py
sculpt/ajax/form_errors.py
sculpt/ajax/forms.py
sculpt/ajax/prototyping.py
sculpt/ajax/responses.py
sculpt/ajax/test_urls.py
sculpt/ajax/views.py